endi/__init__.py
endi/default_layouts.py
endi/exception.py
endi/interfaces.py
endi/log.py
endi/pshell.py
endi/resources.py
endi/alembic/__init__.py
endi/alembic/env.py
endi/alembic/exceptions.py
endi/alembic/script.py.mako
endi/alembic/utils.py
endi/alembic/versions/1_0_432d76e49a9c.py
endi/alembic/versions/1_1_3ffdda6a6fe6.py
endi/alembic/versions/1_2_1f548f8115e8.py
endi/alembic/versions/1_3_1902ba0cc2ac.py
endi/alembic/versions/1_4_2cc9251fb0bb.py
endi/alembic/versions/1_4_adding_polymorphic_i_3f52b6b0ed7c.py
endi/alembic/versions/1_4_ajout_du_statusperso_41116dd5c5c8.py
endi/alembic/versions/1_4_fiche_client_1dce987687aa.py
endi/alembic/versions/1_4_migration_des_factur_14b76f64614c.py
endi/alembic/versions/1_4_migration_du_code_cl_209c0f6d7620.py
endi/alembic/versions/1_4_renommage_des_colonn_1e7d7781a47b.py
endi/alembic/versions/1_4_taux_de_tva_par_1987a6d83e5f.py
endi/alembic/versions/1_5_address_field_on_23fd141c9484.py
endi/alembic/versions/1_5_champ_adresse_mu_70853b5576c.py
endi/alembic/versions/1_5_migrating_expens_362fc5306d54.py
endi/alembic/versions/1_5_migrating_financ_4a4eba558244.py
endi/alembic/versions/1_5_migrating_paymen_1f07ae132ac8.py
endi/alembic/versions/1_5_migrating_work_u_1212f113f03b.py
endi/alembic/versions/1_5_moving_manualinv_2a7a5275c441.py
endi/alembic/versions/1_5_multiple_client__1cc9ff114346.py
endi/alembic/versions/1_6_migrate_code_com_29299007fe7d.py
endi/alembic/versions/1_7_active_tag_2b29f533fdfc.py
endi/alembic/versions/1_7_add_compte_cg_to_4ce6b915de98.py
endi/alembic/versions/1_7_client_to_custom_3f746e901aa6.py
endi/alembic/versions/1_8_add_a_base_node__1ca3a6ef9c9d.py
endi/alembic/versions/1_8_add_session_id_t_1aa7e3b02b04.py
endi/alembic/versions/1_9_1_add_a_configur_1b3d5402f3e4.py
endi/alembic/versions/2_0_add_codes_for_nd_b04de7c28.py
endi/alembic/versions/2_2_activity_status__15d4152bd5d6.py
endi/alembic/versions/2_3_1_2_3_1_header_and_logo_in_db_40c1f95213d0.py
endi/tests/endi.egg-info/SOURCES.txt
endi/tests/endi.egg-info/dependency_links.txt
endi/tests/endi.egg-info/entry_points.txt
endi/tests/endi.egg-info/requires.txt
endi/tests/endi.egg-info/top_level.txt
moogli_erp-2024.1.0b2.dist-info/LICENSE.txt
moogli_erp-2024.1.0b2.dist-info/METADATA
moogli_erp-2024.1.0b2.dist-info/WHEEL
moogli_erp-2024.1.0b2.dist-info/entry_points.txt
moogli_erp-2024.1.0b2.dist-info/top_level.txt
moogli_erp-2024.1.0b2.dist-info/RECORD
