Metadata-Version: 2.1
Name: moogli-erp
Version: 2024.1.0b2
Summary: Progiciel de gestion pour CAE
Author: Majerti
Author-email: contact@majerti.fr
Keywords: pyramid,business,web
Classifier: License :: OSI Approved :: GNU General Public License v3 (GPLv3)
Classifier: Programming Language :: Python
Classifier: Framework :: Pyramid
Classifier: Topic :: Internet :: WWW/HTTP
Classifier: Topic :: Internet :: WWW/HTTP :: WSGI :: Application
Requires-Python: >=3.7
License-File: LICENSE.txt
Requires-Dist: alembic (==1.6.0)
Requires-Dist: Beaker (==1.11.0)
Requires-Dist: Chameleon (==3.9.0)
Requires-Dist: colander (==1.8.3)
Requires-Dist: ColanderAlchemy
Requires-Dist: Cython (==0.29.14)
Requires-Dist: deform (==2.0.14)
Requires-Dist: deform-extensions (>=0.8)
Requires-Dist: docopt (==0.5.0)
Requires-Dist: endi-base (>=6.7.0)
Requires-Dist: endi-celery (<6.8,>=6.7.7)
Requires-Dist: endi-payment (<2.5,>=2.4.0)
Requires-Dist: factur-x (==2.3)
Requires-Dist: fanstatic (==1.1)
Requires-Dist: filedepot (==0.10.0)
Requires-Dist: httpagentparser (==1.9.5)
Requires-Dist: setuptools (==57.4.0)
Requires-Dist: nh3 (==0.2.14)
Requires-Dist: html5lib (==1.1)
Requires-Dist: traitlets (==4.3.3)
Requires-Dist: ipython (==7.16.0)
Requires-Dist: jedi (==0.17.2)
Requires-Dist: js.bootstrap (==3.3.1)
Requires-Dist: js.chosen (==0.9.14)
Requires-Dist: js.deform (==2.0.14)
Requires-Dist: js.jquery (==1.9.1)
Requires-Dist: js.jquery-form (==3.09)
Requires-Dist: js.jquery-maskedinput (==1.3.1)
Requires-Dist: js.jquery-maskmoney (==3.0.2)
Requires-Dist: js.jquery-sortable (==0.9.12)
Requires-Dist: js.jquery-timepicker-addon (==1.3-1)
Requires-Dist: js.jqueryui (==1.10.3)
Requires-Dist: js.select2 (==4.0.4.post1)
Requires-Dist: js.tinymce (==4.1.5)
Requires-Dist: Mako (==1.1.4)
Requires-Dist: mysqlclient (==2.0.3)
Requires-Dist: openpyxl (==3.1.2)
Requires-Dist: PasteDeploy (==2.1.1)
Requires-Dist: peppercorn (==0.6)
Requires-Dist: Pillow (==8.2.0)
Requires-Dist: plaster-pastedeploy (==0.7)
Requires-Dist: paginate (==0.5.6)
Requires-Dist: paginate-sqlalchemy (==0.3.1)
Requires-Dist: py3o.template (==0.10.0)
Requires-Dist: pyjwkest (==1.3.6)
Requires-Dist: pyparsing (==3.0.9)
Requires-Dist: pyramid (==2.0)
Requires-Dist: pyramid-beaker (==0.8)
Requires-Dist: pyramid-chameleon (==0.3)
Requires-Dist: pyramid-deform (==0.2)
Requires-Dist: pyramid-exclog (==1.0)
Requires-Dist: pyramid-ipython
Requires-Dist: pyramid-layout (==1.0)
Requires-Dist: pyramid-mailer (==0.15.1)
Requires-Dist: pyramid-mako (==1.1.0)
Requires-Dist: pyramid-methodrewrite (==0.2.3)
Requires-Dist: pyramid-services (==2.2)
Requires-Dist: pyramid-tm (==2.4)
Requires-Dist: pyramid-retry (==2.1.1)
Requires-Dist: requests (<3,>=2.26.0)
Requires-Dist: reportlab (==3.1.44)
Requires-Dist: repoze.lru (==0.6)
Requires-Dist: simplejson (==3.3.1)
Requires-Dist: sqla-inspect (>=0.7.5)
Requires-Dist: SQLAlchemy (==1.4.50)
Requires-Dist: transaction (==2.1.2)
Requires-Dist: translationstring (==1.2)
Requires-Dist: Unidecode (==0.04.17)
Requires-Dist: venusian (==1.0)
Requires-Dist: waitress (==2.0.0)
Requires-Dist: WebHelpers2 (==2.0)
Requires-Dist: WebOb (==1.8.7)
Requires-Dist: zope.component (==5.0)
Requires-Dist: zope.deprecation (==4.4.0)
Requires-Dist: zope.event (==4.6)
Requires-Dist: zope.interface (==5.5.2)
Requires-Dist: zope.sqlalchemy (==1.6)
Requires-Dist: odfpy (==1.3.6)
Requires-Dist: pyexcel-io (==0.5.18)
Requires-Dist: WeasyPrint (==52.5)
Requires-Dist: tinycss2 (==1.0.2)
Requires-Dist: cairocffi (==1.1.0)
Requires-Dist: pyvat (==1.3.17)
Requires-Dist: schwifty (==2023.3.0)
Provides-Extra: dev
Requires-Dist: libsass (==0.20.1) ; extra == 'dev'
Requires-Dist: sphinx ; extra == 'dev'
Requires-Dist: pyramid-debugtoolbar ; extra == 'dev'
Requires-Dist: sphinxcontrib.httpdomain ; extra == 'dev'
Requires-Dist: black (==22.3.0) ; extra == 'dev'
Requires-Dist: click (==8.0.3) ; extra == 'dev'
Requires-Dist: flake8 ; extra == 'dev'
Requires-Dist: boussole (==2.0) ; extra == 'dev'
Requires-Dist: pytest (<7.0,>=6.0.2) ; extra == 'dev'
Requires-Dist: freezegun (<1.1,>=1.0.0) ; extra == 'dev'
Requires-Dist: Faker (<5.0,>=4.1.3) ; extra == 'dev'
Requires-Dist: WebTest (<2.1,>=2.0.35) ; extra == 'dev'
Requires-Dist: pre-commit ; extra == 'dev'
